Workbook

Sheet Istruzioni
B1: MODELLO FINANZIARIO — Ecosistema SkillSolutions
B2: Documento interno · i numeri sono TUOI da compilare · giugno 2026
B4: ► COME SI USA
B5: 1) Foglio «Input»: compila SOLO le celle GIALLE coi tuoi numeri reali (3 scenari: Conservativo/Base/Ottimistico).
B6: 2) Foglio «Run-rate (mese 12)»: calcola da solo i ricavi a regime per i 3 scenari.
B7: 3) Foglio «Rampa 12 mesi (Base)»: curva mese-per-mese dello scenario Base (rampa lineare illustrativa).
B9: ► FATTI vs IPOTESI
B10: FATTI oggi: 0 clienti SaaS paganti · 0 MRR · BAD360/BA.IA live · BAD pronto al deploy.
B11: IPOTESI: tutto ciò che scrivi qui è una previsione. I tuoi unici numeri REALI di partenza sono BAD eventi.
B13: ► I DRIVER CHE IL WHITE PAPER NON AVEVA (e la tua critica chiede)
B14: • CAC = costo acquisizione cliente. Se ~0 (passaparola) scrivilo, ma è un rischio: il passaparola non scala.
B15: • Churn = % clienti persi/mese. Su SaaS senza onboarding il churn iniziale è alto.
... B18: ► REGOLA D'ORO: se non hai un numero, non inventarlo — lascialo vuoto e segnalo 'da misurare'.

Sheet Input
A1: INPUT — compila le celle GIALLE (i tuoi numeri reali)
A3: Driver | B3: Conservativo | C3: Base | D3: Ottimistico | E3: Note
A4: — BAD EVENTI (servizio · cassa oggi) —
A5: Eventi / mese | E5: il tuo dato reale
A6: Ticket medio (€/evento) | E6: ricavo medio per evento
A7: Margine lordo % | E7: es. 0,55
A8: — BAD CONSULTANCY (retainer) —
A9: Clienti Consultancy a regime (#) | E9: Metodo Bar/Hotel Pro
A10: Fee mensile (€/cliente) | E10: vedi pricing
A11: — BAD360 (SaaS) —
A12: BAD360 clienti paganti (#)
A13: BAD360 ARPU (€/mese) | E13: ricavo medio/cliente
A14: — BA.IA (SaaS + success fee) —
A15: BA.IA clienti paganti (#)
A16: BA.IA ARPU (€/mese)
A17: BA.IA success fee equiv. (€/mese) | E17: % bando vinto, spalmata
A18: — BARMANMATCH —
A19: Venue paganti (#) | E19: i lavoratori sono gratis
A20: Subscription venue (€/mese)
A21: GMV / mese (€) | E21: volume transato
A22: Take rate % | E22: es. 0,10
A23: — SSFORMAZIONE (valuta PAUSA) —
A24: Corsi / mese (#) | E24: 0 se in pausa
A25: Prezzo medio corso (€)
A26: — COSTI & ACQUISIZIONE —
A27: Costi fissi / mese (€) | E27: hosting, tool, dominio…
A28: CAC medio (€/cliente) | E28: 0 se solo passaparola (=rischio)
A29: Churn SaaS %/mese | E29: clienti persi/mese

Sheet Run-rate (mese 12)
A1: RICAVI A REGIME — mese 12 (calcolati)
A3: Voce (€/mese) | B3: Conservativo | C3: Base | D3: Ottimistico
A4: BAD eventi (servizio) | B4: =Input!B5*Input!B6*Input!B7 | C4: =Input!C5*Input!C6*Input!C7 | D4: =Input!D5*Input!D6*Input!D7
A5: BAD Consultancy | B5: =Input!B9*Input!B10 | C5: =Input!C9*Input!C10 | D5: =Input!D9*Input!D10
A6: BAD360 | B6: =Input!B12*Input!B13 | C6: =Input!C12*Input!C13 | D6: =Input!D12*Input!D13
A7: BA.IA | B7: =Input!B15*Input!B16+Input!B17 | C7: =Input!C15*Input!C16+Input!C17 | D7: =Input!D15*Input!D16+Input!D17
A8: BarmanMatch | B8: =Input!B19*Input!B20+Input!B21*Input!B22 | C8: =Input!C19*Input!C20+Input!C21*Input!C22 | D8: =Input!D19*Input!D20+Input!D21*Input!D22
A9: SSFormazione | B9: =Input!B24*Input!B25 | C9: =Input!C24*Input!C25 | D9: =Input!D24*Input!D25
A10: RICAVO TOTALE / mese | B10: =SUM(B4:B9) | C10: =SUM(C4:C9) | D10: =SUM(D4:D9)
A11: di cui ricorrente (MRR) | B11: =B5+B6+B7+B8 | C11: =C5+C6+C7+C8 | D11: =D5+D6+D7+D8
A12: Costi fissi / mese | B12: =Input!B27 | C12: =Input!C27 | D12: =Input!D27
A13: CONTRIBUZIONE / mese | B13: =B10-B12 | C13: =C10-C12 | D13: =D10-D12
A14: % da servizio (BAD eventi) | B14: =IF(B10=0,0,B4/B10) | C14: =IF(C10=0,0,C4/C10) | D14: =IF(D10=0,0,D4/D10)

Sheet Rampa 12 mesi (Base)
A1: RAMPA 12 MESI — scenario Base (rampa lineare illustrativa, €/mese)
A2: Nota: rampa lineare 0→run-rate. La realtà è una S-curve; serve per ordine di grandezza.
A4: Mese | B4: BAD eventi | C4: Consultancy | D4: BAD360 | E4: BA.IA | F4: BarmanMatch | G4: SSForm. | H4: TOTALE
A5: 1 | B5: ='Run-rate (mese 12)'!C4*1/12 | C5: ='Run-rate (mese 12)'!C5*1/12 | D5: ='Run-rate (mese 12)'!C6*1/12 | E5: ='Run-rate (mese 12)'!C7*1/12 | F5: ='Run-rate (mese 12)'!C8*1/12 | G5: ='Run-rate (mese 12)'!C9*1/12 | H5: =SUM(B5:G5)
A6: 2 | B6: ='Run-rate (mese 12)'!C4*2/12 | C6: ='Run-rate (mese 12)'!C5*2/12 | D6: ='Run-rate (mese 12)'!C6*2/12 | E6: ='Run-rate (mese 12)'!C7*2/12 | F6: ='Run-rate (mese 12)'!C8*2/12 | G6: ='Run-rate (mese 12)'!C9*2/12 | H6: =SUM(B6:G6)
A7: 3 | B7: ='Run-rate (mese 12)'!C4*3/12 | C7: ='Run-rate (mese 12)'!C5*3/12 | D7: ='Run-rate (mese 12)'!C6*3/12 | E7: ='Run-rate (mese 12)'!C7*3/12 | F7: ='Run-rate (mese 12)'!C8*3/12 | G7: ='Run-rate (mese 12)'!C9*3/12 | H7: =SUM(B7:G7)
A8: 4 | B8: ='Run-rate (mese 12)'!C4*4/12 | C8: ='Run-rate (mese 12)'!C5*4/12 | D8: ='Run-rate (mese 12)'!C6*4/12 | E8: ='Run-rate (mese 12)'!C7*4/12 | F8: ='Run-rate (mese 12)'!C8*4/12 | G8: ='Run-rate (mese 12)'!C9*4/12 | H8: =SUM(B8:G8)
A9: 5 | B9: ='Run-rate (mese 12)'!C4*5/12 | C9: ='Run-rate (mese 12)'!C5*5/12 | D9: ='Run-rate (mese 12)'!C6*5/12 | E9: ='Run-rate (mese 12)'!C7*5/12 | F9: ='Run-rate (mese 12)'!C8*5/12 | G9: ='Run-rate (mese 12)'!C9*5/12 | H9: =SUM(B9:G9)
A10: 6 | B10: ='Run-rate (mese 12)'!C4*6/12 | C10: ='Run-rate (mese 12)'!C5*6/12 | D10: ='Run-rate (mese 12)'!C6*6/12 | E10: ='Run-rate (mese 12)'!C7*6/12 | F10: ='Run-rate (mese 12)'!C8*6/12 | G10: ='Run-rate (mese 12)'!C9*6/12 | H10: =SUM(B10:G10)
A11: 7 | B11: ='Run-rate (mese 12)'!C4*7/12 | C11: ='Run-rate (mese 12)'!C5*7/12 | D11: ='Run-rate (mese 12)'!C6*7/12 | E11: ='Run-rate (mese 12)'!C7*7/12 | F11: ='Run-rate (mese 12)'!C8*7/12 | G11: ='Run-rate (mese 12)'!C9*7/12 | H11: =SUM(B11:G11)
A12: 8 | B12: ='Run-rate (mese 12)'!C4*8/12 | C12: ='Run-rate (mese 12)'!C5*8/12 | D12: ='Run-rate (mese 12)'!C6*8/12 | E12: ='Run-rate (mese 12)'!C7*8/12 | F12: ='Run-rate (mese 12)'!C8*8/12 | G12: ='Run-rate (mese 12)'!C9*8/12 | H12: =SUM(B12:G12)
A13: 9 | B13: ='Run-rate (mese 12)'!C4*9/12 | C13: ='Run-rate (mese 12)'!C5*9/12 | D13: ='Run-rate (mese 12)'!C6*9/12 | E13: ='Run-rate (mese 12)'!C7*9/12 | F13: ='Run-rate (mese 12)'!C8*9/12 | G13: ='Run-rate (mese 12)'!C9*9/12 | H13: =SUM(B13:G13)
A14: 10 | B14: ='Run-rate (mese 12)'!C4*10/12 | C14: ='Run-rate (mese 12)'!C5*10/12 | D14: ='Run-rate (mese 12)'!C6*10/12 | E14: ='Run-rate (mese 12)'!C7*10/12 | F14: ='Run-rate (mese 12)'!C8*10/12 | G14: ='Run-rate (mese 12)'!C9*10/12 | H14: =SUM(B14:G14)
A15: 11 | B15: ='Run-rate (mese 12)'!C4*11/12 | C15: ='Run-rate (mese 12)'!C5*11/12 | D15: ='Run-rate (mese 12)'!C6*11/12 | E15: ='Run-rate (mese 12)'!C7*11/12 | F15: ='Run-rate (mese 12)'!C8*11/12 | G15: ='Run-rate (mese 12)'!C9*11/12 | H15: =SUM(B15:G15)
A16: 12 | B16: ='Run-rate (mese 12)'!C4*12/12 | C16: ='Run-rate (mese 12)'!C5*12/12 | D16: ='Run-rate (mese 12)'!C6*12/12 | E16: ='Run-rate (mese 12)'!C7*12/12 | F16: ='Run-rate (mese 12)'!C8*12/12 | G16: ='Run-rate (mese 12)'!C9*12/12 | H16: =SUM(B16:G16)
A17: Cassa 12m | B17: =SUM(B5:B16) | C17: =SUM(C5:C16) | D17: =SUM(D5:D16) | E17: =SUM(E5:E16) | F17: =SUM(F5:F16) | G17: =SUM(G5:G16) | H17: =SUM(H5:H16)
